{
    "meta": {
        "schema": "cipher-content.v1",
        "exported_at": "2026-05-30T11:57:27+00:00",
        "category_alias": "classical-ciphers",
        "cipher_alias": "caesar",
        "language": "ru",
        "default_language": "en",
        "cipher_id": 11,
        "category_id": 2
    },
    "cipher_translation": {
        "id": 11,
        "data": {
            "name": "Шифр Цезаря",
            "name_short": "Шифр Цезаря",
            "description": "Шифруйте и расшифровывайте текст шифром Цезаря онлайн: задавайте свой сдвиг и выбирайте разные алфавиты. Это один из самых старых и известных классических методов шифрования.",
            "description_stort": "Классический шифр со сдвигом букв и настраиваемым значением сдвига.",
            "meta_title": "Шифр Цезаря онлайн: шифратор и дешифратор",
            "meta_description": "Используйте шифр Цезаря онлайн, чтобы шифровать и расшифровывать текст с заданным сдвигом, разными алфавитами и мгновенным результатом."
        }
    },
    "blocks": [
        {
            "id": 35,
            "sort_order": 10,
            "published": true,
            "data": {
                "title": "Как работает шифр Цезаря",
                "text": "<p>Шифр Цезаря — это шифр простой замены, в котором каждая буква выбранного алфавита сдвигается на фиксированное число позиций. Например, в русском алфавите при сдвиге 3 буква А превращается в Г, Б — в Д, а В — в Е.</p><p>При шифровании буквы смещаются вперёд по алфавиту, а при расшифровании — назад на то же значение сдвига. Пробелы, цифры и знаки препинания обычно остаются без изменений.</p><p>Из-за простоты и предсказуемости этот метод часто используют для знакомства с базовыми понятиями классической криптографии: открытым текстом, шифртекстом, ключом, шифрованием и расшифрованием.</p>"
            }
        },
        {
            "id": 36,
            "sort_order": 20,
            "published": true,
            "data": {
                "title": "Безопасность и практические ограничения",
                "text": "<p>По современным меркам шифр Цезаря не считается надёжным. Возможных значений сдвига мало, поэтому атакующий может очень быстро перебрать все варианты.</p><p>Несмотря на слабость, шифр полезен для обучения, головоломок и демонстраций: он наглядно показывает, как секретный параметр превращает читаемый текст в шифртекст.</p><p>Если нужно автоматически восстановить неизвестный сдвиг, используйте взломщик шифра Цезаря для поиска ключа и анализа.</p>"
            }
        },
        {
            "id": 48,
            "sort_order": 30,
            "published": true,
            "data": {
                "title": "История шифра Цезаря",
                "text": "<p>Шифр назван в честь Юлия Цезаря, с которым традиционно связывают использование сдвига букв для защиты военных сообщений.</p><p>Сегодня этот метод крайне слаб, но он остаётся одним из самых узнаваемых исторических шифров и удобной отправной точкой для изучения шифров замены.</p>"
            }
        }
    ],
    "faq": [
        {
            "id": 85,
            "sort_order": 10,
            "published": true,
            "data": {
                "question": "Надёжен ли шифр Цезаря?",
                "answer": "Нет. Шифр Цезаря быстро перебирается, потому что возможных сдвигов ограниченное число. Его лучше использовать для обучения, головоломок и простых демонстраций."
            }
        },
        {
            "id": 86,
            "sort_order": 20,
            "published": true,
            "data": {
                "question": "Можно ли использовать нелатинский текст?",
                "answer": "Да. Перед обработкой текста выберите подходящий алфавит в настройках."
            }
        },
        {
            "id": 87,
            "sort_order": 30,
            "published": true,
            "data": {
                "question": "Что происходит с пробелами и пунктуацией?",
                "answer": "Пробелы, цифры и специальные символы не меняются. Шифруются только буквы из выбранного алфавита."
            }
        },
        {
            "id": 88,
            "sort_order": 40,
            "published": true,
            "data": {
                "question": "Почему он называется шифром Цезаря?",
                "answer": "Шифр назван в честь Юлия Цезаря: по традиционной версии, он использовал метод сдвига букв для защиты военной переписки."
            }
        },
        {
            "id": 89,
            "sort_order": 50,
            "published": true,
            "data": {
                "question": "Что такое живой режим?",
                "answer": "Живой режим автоматически пересчитывает результат, когда вы меняете текст или настройки шифрования. Так результат виден сразу, без нажатия кнопки."
            }
        },
        {
            "id": 90,
            "sort_order": 60,
            "published": true,
            "data": {
                "question": "Можно ли этим инструментом взломать шифр Цезаря?",
                "answer": "Этот мини-инструмент предназначен для шифрования и расшифрования, когда сдвиг уже известен. Для автоматического поиска ключа и частотного анализа используйте взломщик шифра Цезаря."
            }
        }
    ],
    "examples": [
        {
            "id": 1,
            "sort_order": 10,
            "published": true,
            "direction": "",
            "data": {
                "title": "Шифрование со сдвигом 3",
                "key": "",
                "shift": 3,
                "input": "ПРИВЕТ МИР",
                "output": "ТУЛЕЗХ ПЛУ",
                "description": "Алфавит: русский. Сдвиг: 3. Режим: шифрование. Каждая буква сдвигается на три позиции вперёд."
            }
        },
        {
            "id": 2,
            "sort_order": 20,
            "published": true,
            "direction": "",
            "data": {
                "title": "Расшифрование со сдвигом 3",
                "key": "",
                "shift": 3,
                "input": "ТУЛЕЗХ ПЛУ",
                "output": "ПРИВЕТ МИР",
                "description": "Алфавит: русский. Сдвиг: 3. Режим: расшифрование. Тот же сдвиг применяется в обратную сторону, чтобы восстановить исходный текст."
            }
        },
        {
            "id": 23,
            "sort_order": 30,
            "published": true,
            "direction": "",
            "data": {
                "title": "Пример со сдвигом 13",
                "key": "",
                "shift": 13,
                "input": "ПРИВЕТ",
                "output": "ЬЭХОСЯ",
                "description": "Алфавит: русский. Сдвиг: 13. Такой вариант показывает тот же принцип, что и ROT13 в английском алфавите: текст скрывается фиксированным сдвигом."
            }
        },
        {
            "id": 24,
            "sort_order": 40,
            "published": true,
            "direction": "",
            "data": {
                "title": "Сохранение пробелов и пунктуации",
                "key": "",
                "shift": 5,
                "input": "ПРИВЕТ, МИР!",
                "output": "ФХНЖЙЧ, СНХ!",
                "description": "Сдвигаются только буквы. Пробелы, знаки препинания и другие символы остаются без изменений."
            }
        }
    ],
    "tags": [
        {
            "id": 47,
            "sort_order": 10,
            "published": true,
            "data": {
                "tag": "Шифр со сдвигом"
            }
        },
        {
            "id": 48,
            "sort_order": 20,
            "published": true,
            "data": {
                "tag": "Классическая криптография"
            }
        },
        {
            "id": 49,
            "sort_order": 30,
            "published": true,
            "data": {
                "tag": "Обучение"
            }
        },
        {
            "id": 78,
            "sort_order": 40,
            "published": true,
            "data": {
                "tag": "Шифр замены"
            }
        },
        {
            "id": 79,
            "sort_order": 50,
            "published": true,
            "data": {
                "tag": "ROT13"
            }
        },
        {
            "id": 80,
            "sort_order": 60,
            "published": true,
            "data": {
                "tag": "Юлий Цезарь"
            }
        }
    ],
    "notes": [
        "Сохраняйте id у каждой сущности без изменений.",
        "Менять нужно только текстовые поля в data.",
        "В blocks.data.text используйте HTML-разметку: минимум один <p>, можно несколько <p>; также допустимы списки <ul>/<ol> с <li>.",
        "Пустые строки допустимы: при импорте это удалит перевод для конкретного языка.",
        "Для добавления новых элементов в sections blocks/faq/examples/tags создавайте объект без id или с id=0: импорт создаст запись автоматически.",
        "Новые элементы (без id / с id=0) разрешено добавлять только в файле, где meta.language == meta.default_language."
    ]
}
